my_awesome_package_jhs-0.1.0.dist-info/licenses/LICENSE
test_project_name/__init__.py
test_project_name/simple_math.py
my_awesome_package_jhs-0.1.0.dist-info/METADATA
my_awesome_package_jhs-0.1.0.dist-info/WHEEL
my_awesome_package_jhs-0.1.0.dist-info/top_level.txt
my_awesome_package_jhs-0.1.0.dist-info/RECORD
