Metadata-Version: 2.4
Name: my-awesome-package-jhs
Version: 0.1.0
Summary: A short description of my project.
Author-email: 홍길동 <hong.gildong@example.com>
Project-URL: Homepage, https://github.com/my-username/my-awesome-package
Project-URL: Issues, https://github.com/my-username/my-awesome-package/issues
Classifier: Programming Language :: Python :: 3
Classifier: License :: OSI Approved :: MIT License
Classifier: Operating System :: OS Independent
Requires-Python: >=3.7
License-File: LICENSE
Requires-Dist: requests
Requires-Dist: beautifulsoup4
Dynamic: license-file
